[
    {
	      "title":"Making Good Instructors Great",
	      "author":"Eduworks",
	      "coverHref": "bookshelf/MGIG-cover.png",
	      "rootUrl":"bookshelf/epub3-mgig.epub",
        "version":1
    },
    {
        "title":"CyberSec",
        "author":"Eduworks",
        "coverHref":"bookshelf/COVER-IMAGE.png",
        "rootUrl":"bookshelf/PeBL_CyberSec_v12b.epub",
        "version":1
    },
    {
        "title":"eReader Test Book",
        "author":"Eduworks",
        "coverHref":"bookshelf/PeBL_Test_Cover.png",
        "rootUrl":"bookshelf/PeBL_Test_Book.epub",
        "version":1
    }
]
